.DS_Store
hypercluster/__init__.py
hypercluster/additional_clusterers.py
hypercluster/additional_metrics.py
hypercluster/classes.py
hypercluster/clustering.py
hypercluster/constants.py
hypercluster/evaluations.py
hypercluster/metrics.py
hypercluster/utilities.py
hypercluster/visualize.py
hypercluster/tests/__init__.py
hypercluster/tests/test_clustering.py
hypercluster/tests/test_visualize.py
tests/__init__.py
tests/test_clustering.py
tests/test_snakemake.py
tests/test_visualize.py
hypercluster-0.1.13.dist-info/LICENSE
hypercluster-0.1.13.dist-info/METADATA
hypercluster-0.1.13.dist-info/WHEEL
hypercluster-0.1.13.dist-info/top_level.txt
hypercluster-0.1.13.dist-info/RECORD
