Metadata-Version: 2.1
Name: hypercluster
Version: 0.1.13
Summary: A package for automatic clustering hyperparameter optmization
Home-page: https://github.com/liliblu/hypercluster
Author: Lili Blumenberg, Ruggles Lab
Author-email: lili.blumenberg@gmail.com
License: UNKNOWN
Platform: UNKNOWN
Classifier: Programming Language :: Python :: 3.7
Classifier: License :: OSI Approved :: MIT License
Classifier: Operating System :: MacOS
Classifier: Operating System :: Unix
Requires-Dist: pandas (>=0.24.2)
Requires-Dist: numpy (>=1.16.4)
Requires-Dist: scipy (>=1.2.1)
Requires-Dist: matplotlib (>=3.1.0)
Requires-Dist: seaborn (>=0.9.0)
Requires-Dist: scikit-learn (>=0.22.0)
Requires-Dist: hdbscan (>=0.8.24)
Requires-Dist: snakemake (>=5.8.2)
Requires-Dist: python-igraph (>=0.7.1)
Requires-Dist: leidenalg (>=0.7.0)
Requires-Dist: louvain (>=0.6.1)
